kloch/__init__.py
kloch/__main__.py
kloch/_dictmerge.py
kloch/_utils.py
kloch/cli.py
kloch/config.py
kloch/constants.py
kloch/filesyntax/__init__.py
kloch/filesyntax/_io.py
kloch/filesyntax/_profile.py
kloch/launchers/__init__.py
kloch/launchers/_context.py
kloch/launchers/_get.py
kloch/launchers/_platform.py
kloch/launchers/_plugins.py
kloch/launchers/_serialized.py
kloch/launchers/base/__init__.py
kloch/launchers/base/_dataclass.py
kloch/launchers/base/_serialized.py
kloch/launchers/python/__init__.py
kloch/launchers/python/_dataclass.py
kloch/launchers/python/_serialized.py
kloch/launchers/system/__init__.py
kloch/launchers/system/_dataclass.py
kloch/launchers/system/_serialized.py
kloch/session.py
kloch-0.13.0.dist-info/LICENSE.txt
kloch-0.13.0.dist-info/METADATA
kloch-0.13.0.dist-info/WHEEL
kloch-0.13.0.dist-info/entry_points.txt
kloch-0.13.0.dist-info/RECORD
