Metadata-Version: 2.1
Name: kloch
Version: 0.13.0
Summary: Environment Manager CLI wrapping package managers calls as serialized config file
License: LICENSE.txt
Keywords: environment,kloch,packaging,managing
Author: Liam Collod
Author-email: monsieurlixm@gmail.com
Requires-Python: >=3.7
Classifier: Development Status :: 4 - Beta
Classifier: Intended Audience :: Developers
Classifier: License :: Other/Proprietary License
Classifier: Programming Language :: Python :: 3
Classifier: Programming Language :: Python :: 3.7
Classifier: Programming Language :: Python :: 3.8
Classifier: Programming Language :: Python :: 3.9
Classifier: Programming Language :: Python :: 3.10
Classifier: Programming Language :: Python :: 3.11
Classifier: Programming Language :: Python :: 3.12
Classifier: Programming Language :: Python :: 3.13
Provides-Extra: dev
Provides-Extra: doc
Provides-Extra: tests
Requires-Dist: PyYAML (>=6.0.1,<7.0.0)
Requires-Dist: Sphinx (>=7.3.7,<8.0.0) ; (python_version >= "3.9") and (extra == "doc")
Requires-Dist: black (>=24.4.2,<25.0.0) ; (python_version >= "3.9") and (extra == "dev")
Requires-Dist: furo (>=2024.4.27,<2025.0.0) ; (python_version >= "3.9") and (extra == "doc")
Requires-Dist: myst_parser (>=3,<4) ; (python_version >= "3.9" and python_version < "3.13") and (extra == "doc")
Requires-Dist: pytest (==7.3.2) ; (python_version >= "3.7") and (extra == "tests")
Requires-Dist: sphinx-autobuild (==2024.2.4) ; (python_version >= "3.9") and (extra == "doc")
Requires-Dist: sphinx-copybutton (==0.5) ; (python_version >= "3.9") and (extra == "doc")
Requires-Dist: sphinx-exec-code (==0.12) ; (python_version >= "3.9") and (extra == "doc")
Requires-Dist: typing-extensions (<4.8) ; extra == "tests"
Project-URL: Documentation, https://knotsanimation.github.io/kloch/
Project-URL: github, https://github.com/knotsanimation/kloch
Project-URL: homepage, https://github.com/knotsanimation/kloch
Project-URL: issues, https://github.com/knotsanimation/kloch/issues
Project-URL: releasenotes, https://knotsanimation.github.io/kloch/changelog.html
